pythonbs/__init__.py
pythonbs-0.0.2.dist-info/LICENSE
pythonbs-0.0.2.dist-info/METADATA
pythonbs-0.0.2.dist-info/WHEEL
pythonbs-0.0.2.dist-info/top_level.txt
pythonbs-0.0.2.dist-info/RECORD
