Metadata-Version: 2.1
Name: pythonbs
Version: 0.0.2
Summary: A python client for running tests in browserstack
Home-page: UNKNOWN
Author: Rohan Joshi
Author-email: rohan.j@qxf2.com
License: UNKNOWN
Platform: UNKNOWN
Classifier: Programming Language :: Python :: 3
Classifier: License :: OSI Approved :: MIT License
Classifier: Operating System :: OS Independent
